icpquery-1.3.0.dist-info/METADATA
icpquery-1.3.0.dist-info/WHEEL
icpquery-1.3.0.dist-info/entry_points.txt
icpquery-1.3.0.dist-info/licenses/LICENSE
icpquery/__init__.py
icpquery/__main__.py
icpquery/backgrounds/attic.png
icpquery/backgrounds/basket1.png
icpquery/backgrounds/basket2.png
icpquery/backgrounds/beach.png
icpquery/backgrounds/bee.png
icpquery/backgrounds/bike.png
icpquery/backgrounds/bridge1.png
icpquery/backgrounds/bridge2.png
icpquery/backgrounds/butterfly.png
icpquery/backgrounds/butterfly_flower1.png
icpquery/backgrounds/butterfly_flower2.png
icpquery/backgrounds/butterfly_flower3.png
icpquery/backgrounds/butterfly_flower4.png
icpquery/backgrounds/butterfly_flower5.png
icpquery/backgrounds/butterfly_flower6.png
icpquery/backgrounds/cactus.png
icpquery/backgrounds/cake.png
icpquery/backgrounds/camera.png
icpquery/backgrounds/car.png
icpquery/backgrounds/cat1.png
icpquery/backgrounds/cat2.png
icpquery/backgrounds/cat3.png
icpquery/backgrounds/chrysanthemum1.png
icpquery/backgrounds/chrysanthemum2.png
icpquery/backgrounds/city.png
icpquery/backgrounds/coast_park.png
icpquery/backgrounds/corn_field.png
icpquery/backgrounds/dahlia1.png
icpquery/backgrounds/dahlia2.png
icpquery/backgrounds/deer.png
icpquery/backgrounds/dna.png
icpquery/backgrounds/doll.png
icpquery/backgrounds/duck1.png
icpquery/backgrounds/duck2.png
icpquery/backgrounds/falls.png
icpquery/backgrounds/foxtail_grass.png
icpquery/backgrounds/grasshopper.png
icpquery/backgrounds/grassland1.png
icpquery/backgrounds/grassland2.png
icpquery/backgrounds/grassland3.png
icpquery/backgrounds/grassland4.png
icpquery/backgrounds/grassland5.png
icpquery/backgrounds/horse.png
icpquery/backgrounds/horse_herd.png
icpquery/backgrounds/hummingbird.png
icpquery/backgrounds/leaves1.png
icpquery/backgrounds/leaves2.png
icpquery/backgrounds/leaves3.png
icpquery/backgrounds/leaves4.png
icpquery/backgrounds/lion.png
icpquery/backgrounds/living_room1.png
icpquery/backgrounds/living_room2.png
icpquery/backgrounds/magic.png
icpquery/backgrounds/moon.png
icpquery/backgrounds/morning_glory.png
icpquery/backgrounds/pampas_grass.png
icpquery/backgrounds/peach.png
icpquery-1.3.0.dist-info/RECORD
