Metadata-Version: 2.1
Name: icpquery
Version: 1.3.0
Summary: A CLI tool for query keyword in China MIIT ICP Website to get ICP Record
Keywords: MIIT,ICP
Author-Email: SocialSisterYi <1440239038@qq.com>
License: MIT
Project-URL: repository, https://github.com/SocialSisterYi/ICPQuery
Requires-Python: >=3.11
Requires-Dist: rich>=14.2.0
Requires-Dist: typer>=0.15.0
Requires-Dist: numpy>=2.3.0
Requires-Dist: pydantic>=2.11
Requires-Dist: pycryptodome>=3.23
Requires-Dist: opencv-python>=4.10
Requires-Dist: onnxruntime>=1.21
Requires-Dist: httpx>=0.28
